Workbook

Sheet Alumni AG
A1: 🌱 Alumni Gaea21 pour AG — 510 personnes
A2: ID | B2: Prénom | C2: Nom | D2: Année sortie | E2: Fonction Gaea21 | F2: Type contrat | G2: Date entrée | H2: Date sortie | I2: Statut Alumni | J2: — LinkedIn — | K2: Poste actuel | L2: Entreprise | M2: Ville | N2: Pays | O2: Secteur | P2: URL LinkedIn | Q2: Statut enrich. | R2: Notes
A3: 2 | B3: Khaled | C3: ABDELHAK | D3: 2023 | E3: IT | F3: Bénévole | G3: 2023-03-02 | H3: 2023-09-02 | Q3: ⬜ À enrichir
A4: 6 | B4: Conan Sherlock | C4: ABOUTOU | D4: 2023 | E4: Statistiques | F4: Bénévole | G4: 2023-02-08 | H4: 2023-11-03 | Q4: ⬜ À enrichir
A5: 8 | B5: Imane | C5: ACHOURI | D5: 2023 | E5: scientifique | F5: Bénévole | G5: 2023-05-10 | H5: 2023-11-17 | Q5: ⬜ À enrichir
A6: 9 | B6: Manuela | C6: ACOSTA | D6: 2023 | E6: RH | F6: Bénévole | G6: 2023-03-01 | H6: 2023-06-02 | Q6: ⬜ À enrichir
A7: 10 | B7: Annick | C7: ADOUKONOU | D7: 2023 | E7: GCBO / Restuaration durable | F7: Bénévole | G7: 2023-08-07 | H7: 2023-12-15 | Q7: ⬜ À enrichir
A8: 12 | B8: Nour | C8: AFFES | D8: 2023 | E8: IT | F8: Conventioné | G8: 2022-06-09 | H8: 2023-02-03 | Q8: ⬜ À enrichir
A9: 16 | B9: Pélé Patrice | C9: AHOUDJI | D9: 2023 | E9: CCDSP - smart cities, recherche et AG recherche | F9: Bénévole | G9: 2023-10-10 | H9: 2024-05-03 | Q9: ⬜ À enrichir
A10: 17 | B10: Mame Lala | C10: AICHA DIENG | D10: 2023 | E10: Statistiques | F10: Conventioné | G10: 2023-12-11 | H10: 2024-07-05 | Q10: ⬜ À enrichir
A11: 20 | B11: Tolgahan | C11: ALGUL | D11: 2023 | E11: Partenariat et expension | F11: Conventioné | G11: 2023-02-05 | H11: 2023-03-08 | I11: Non | Q11: ⬜ À enrichir
A12: 24 | B12: Emmanuelle | C12: AMBERT | D12: 2023 | E12: Traduction | F12: Conventioné | G12: 2023-04-11 | H12: 2023-08-10 | Q12: ⬜ À enrichir
A13: 26 | B13: Gary | C13: AMECIA | D13: 2023 | E13: Budget / osez entrepreunariat | F13: Conventioné | G13: 2023-01-16 | H13: 2023-07-14 | Q13: ⬜ À enrichir
A14: 28 | B14: Carmen | C14: AMOUH | D14: 2023 | E14: rh | F14: Bénévole | G14: 2023-01-18 | H14: 2025-12-14 | I14: Alumni gratuit | Q14: ⬜ À enrichir
A15: 30 | B15: Holy Marlène | C15: ANDRIAMASY | D15: 2023 | E15: Data analyst | F15: Bénévole | G15: 2023-01-16 | H15: 2023-04-14 | Q15: ⬜ À enrichir
A16: 34 | B16: Arzu | C16: ARDICLI | D16: 2023 | E16: Cartographie/ eco mobilité | F16: Bénévole | G16: 2022-12-05 | H16: 2023-06-09 | Q16: ⬜ À enrichir
A17: 38 | B17: Foteini | C17: ATHANASOPOULOU | D17: 2023 | E17: Eco-conso scientifique | F17: Bénévole | G17: 2022-11-09 | H17: 2023-05-26 | Q17: ⬜ À enrichir
A18: 40 | B18: Edouard | C18: AUSSEDAT | D18: 2023 | E18: Formateur pédagogique | F18: Bénévole | G18: 2022-08-30 | H18: 2023-03-17 | I18: Alumni gratuit | Q18: ⬜ À enrichir
A19: 44 | B19: Arhamatou | C19: Abdourhamane | D19: 2023 | E19: Budget/ Pré-Analayse | F19: Conventioné | G19: 2023-06-13 | H19: 2023-09-15 | Q19: ⬜ À enrichir
A20: 52 | B20: Kumud | C20: BADERIYA | D20: 2023 | E20: PAC/ Green id | F20: Bénévole | G20: 2022-11-03 | H20: 2023-05-26 | Q20: ⬜ À enrichir
A21: 53 | B21: AROUA | C21: BALAYIRA | D21: 2023 | E21: Budget Admin/ osez l'entrpreunariat | F21: Conventioné | G21: 2023-06-12 | H21: 2023-12-15 | Q21: ⬜ À enrichir
A22: 57 | B22: Aurélie | C22: BARBIER | D22: 2023 | E22: Coach | F22: Bénévole | G22: 2023-04-19 | H22: 2023-10-20 | Q22: ⬜ À enrichir
A23: 58 | B23: Benjamin | C23: BARDET | D23: 2023 | E23: IT | F23: Conventioné | G23: 2023-02-03 | H23: 2023-05-19 | Q23: ⬜ À enrichir
A24: 59 | B24: Mahdi | C24: BECHIM | D24: 2023 | E24: RH | F24: Bénévole | G24: 2023-06-28 | H24: 2023-09-29 | Q24: ⬜ À enrichir
A25: 62 | B25: Bradley | C25: BELINGA | D25: 2023 | E25: CM/ Branding/ Partenariat | F25: Bénévole | G25: 2023-03-07 | H25: 2023-09-08 | Q25: ⬜ À enrichir
A26: 67 | B26: Hafedh | C26: BEN DHIA | D26: 2023 | E26: IT | F26: Bénévole | G26: 2023-06-15 | H26: 2023-09-15 | Q26: ⬜ À enrichir
A27: 70 | B27: Oumayma | C27: BEN RACHED | D27: 2023 | E27: éco geste et Scientifique | F27: Bénévole | G27: 2023-04-03 | H27: 2023-10-06 | Q27: ⬜ À enrichir
A28: 71 | B28: Amira | C28: BEN SOLTANE | D28: 2023 | E28: Statistiques/ Formation | F28: Conventioné | G28: 2023-12-12 | H28: 2024-05-31 | Q28: ⬜ À enrichir
A29: 72 | B29: Rayan | C29: BENGUEDIH | D29: 2023 | E29: Statistiques | F29: Bénévole | G29: 2023-04-04 | H29: 2023-08-04 | I29: Alumni gratuit | Q29: ⬜ À enrichir
A30: 74 | B30: Enzo | C30: BIANCU | D30: 2023 | E30: CM/ Partenariat | F30: Conventioné | G30: 2023-01-31 | H30: 2023-07-28 | Q30: ⬜ À enrichir
A31: 75 | B31: Aïcha | C31: BIBI | D31: 2023 | E31: IT | F31: Conventioné | G31: 2023-04-20 | H31: 2023-09-20 | Q31: ⬜ À enrichir
A32: 78 | B32: Bouwèreou | C32: BIGNAN-KAGOMNA | D32: 2023 | E32: GCBO/ architecture /publication | F32: Bénévole | G32: 2023-07-08 | H32: 2023-11-10 | Q32: ⬜ À enrichir
A33: 80 | B33: Andy | C33: BLONDELLE | D33: 2023 | E33: IT | F33: Conventioné | G33: 2023-01-03 | H33: 2023-04-14 | Q33: ⬜ À enrichir
A34: 81 | B34: Lobna | C34: BOUALLEGUE | D34: 2023 | E34: IT | F34: Conventioné | G34: 2023-05-04 | H34: 2023-11-03 | Q34: ⬜ À enrichir
A35: 84 | B35: Julie | C35: BOURGERY | D35: 2023 | E35: RH | F35: Bénévole | G35: 2022-04-06 | H35: 2022-10-07 | Q35: ⬜ À enrichir
A36: 85 | B36: Anais | C36: BRANDT | D36: 2023 | E36: Coach | F36: Bénévole | G36: 2023-05-24 | H36: 2023-08-25 | Q36: ⬜ À enrichir
A37: 86 | B37: Jayson | C37: BREMENT | D37: 2023 | E37: IT | F37: Conventioné | G37: 2023-08-24 | H37: 2023-11-15 | Q37: ⬜ À enrichir
A38: 87 | B38: Bénedicte | C38: BROCHU | D38: 2023 | E38: Coach | F38: Bénévole | G38: 2022-09-12 | H38: 2023-04-07 | Q38: ⬜ À enrichir
A39: 89 | B39: Viviane | C39: BRUNET | D39: 2023 | E39: RH | F39: Conventioné | G39: 2023-04-26 | H39: 2023-07-28 | Q39: ⬜ À enrichir
A40: 91 | B40: Katarina | C40: BUKVIC | D40: 2023 | E40: RH | F40: Conventioné | G40: 2023-03-13 | H40: 2023-06-16 | Q40: ⬜ À enrichir
A41: 93 | B41: Naoufel | C41: Bekkal | D41: 2023 | E41: For mation publication | F41: Bénévole | G41: 2023-03-07 | H41: 2023-09-08 | Q41: ⬜ À enrichir
A42: 94 | B42: Nadia | C42: Benyamina | D42: 2023 | E42: IT | F42: Conventioné | G42: 2023-03-09 | H42: 2023-06-02 | I42: Non | Q42: ⬜ À enrichir
A43: 96 | B43: Samira | C43: Bouzourene | D43: 2023 | E43: coach | F43: Bénévole | G43: 2022-12-20 | H43: 2023-04-14 | I43: Non | Q43: ⬜ À enrichir
A44: 100 | B44: Emma | C44: CAPALDI | D44: 2023 | E44: RH | F44: Bénévole | G44: 2022-11-02 | H44: 2023-05-26 | Q44: ⬜ À enrichir
A45: 103 | B45: Nathalie | C45: CARON | D45: 2023 | E45: RH | F45: Conventioné | G45: 2022-03-23 | H45: 2022-07-22 | Q45: ⬜ À enrichir
A46: 104 | B46: Hajar | C46: CHAABANI | D46: 2023 | E46: IT | F46: Conventioné | G46: 2023-06-22 | H46: 2023-09-22 | Q46: ⬜ À enrichir
A47: 107 | B47: Maxime | C47: CHAPOT | D47: 2023 | E47: IT | F47: Bénévole | G47: 2023-03-16 | H47: 2023-05-12 | Q47: ⬜ À enrichir
A48: 108 | B48: Antoine | C48: CHARLOT | D48: 2023 | E48: IT | F48: Conventioné | G48: 2023-04-06 | H48: 2023-10-06 | Q48: ⬜ À enrichir
A49: 109 | B49: Jordan | C49: CHEUFFA | D49: 2023 | E49: Publication scientifique | F49: Conventioné | G49: 2023-04-17 | H49: 2023-07-21 | Q49: ⬜ À enrichir
A50: 110 | B50: Malek | C50: CHIKHAOUI | D50: 2023 | E50: RH | F50: Bénévole | G50: 2021-11-10 | H50: 2022-05-20 | Q50: ⬜ À enrichir
A51: 111 | B51: Mélina | C51: CHIRIOT | D51: 2023 | E51: IT | F51: Conventioné | G51: 2023-07-20 | H51: 2023-11-24 | Q51: ⬜ À enrichir
A52: 113 | B52: Marine | C52: CHRETIEN | D52: 2023 | E52: Branding/ CM/ Partenariat/ GES/ Fundraising | F52: Conventioné | G52: 2023-04-03 | H52: 2023-06-30 | Q52: ⬜ À enrichir
A53: 115 | B53: Eugénio | C53: CIRILLO | D53: 2023 | E53: Branding / RV | F53: Bénévole | G53: 2023-03-20 | H53: 2023-09-22 | Q53: ⬜ À enrichir
A54: 116 | B54: Dickourou | C54: CISSE | D54: 2023 | E54: Agriculture durable | F54: Bénévole | G54: 2023-03-06 | H54: 2023-09-08 | Q54: ⬜ À enrichir
A55: 118 | B55: Léa | C55: CORREIA | D55: 2023 | E55: Coach | F55: Bénévole | G55: 2023-03-29 | H55: 2023-09-29 | Q55: ⬜ À enrichir
... A65: 140 | B65: Estelle | C65: DESAINTJEAN | D65: 2023 | E65: RH | F65: Bénévole | G65: 2022-11-30 | H65: 2023-06-16 | Q65: ⬜ À enrichir
A66: 144 | B66: Alpha | C66: DIALLO | D66: 2023 | E66: AUCUN DOSSIER | Q66: ⬜ À enrichir
A67: 146 | B67: Gabriela | C67: DIAS | D67: 2023 | E67: Traduction | F67: Conventioné | G67: 2023-04-03 | H67: 2023-06-30 | Q67: ⬜ À enrichir
A68: 147 | B68: Deborah | C68: DIBASANI | D68: 2023 | E68: RH | F68: Bénévole | G68: 2022-11-15 | H68: 2023-06-02 | Q68: ⬜ À enrichir
A69: 148 | B69: Aimé Providence | C69: DIHOULOU | D69: 2023 | E69: RH | F69: Bénévole | G69: 2022-08-10 | H69: 2023-03-03 | Q69: ⬜ À enrichir
A70: 151 | B70: Sabrina | C70: DJIAR | D70: 2023 | E70: RH | F70: Conventioné | G70: 2023-01-18 | H70: 2023-04-14 | Q70: ⬜ À enrichir
A71: 153 | B71: Jenny | C71: DJOUKOUEHI | D71: 2023 | E71: Urbanisme/ RH / Partenariats | F71: Bénévole | G71: 2022-12-13 | H71: 2023-06-30 | Q71: ⬜ À enrichir
A72: 154 | B72: Aissata | C72: DOUMBIA | D72: 2023 | E72: RH | F72: Conventioné | G72: 2023-03-01 | H72: 2023-06-30 | Q72: ⬜ À enrichir
A73: 156 | B73: Yann | C73: DUBOTS | D73: 2023 | E73: RH | F73: Bénévole | G73: 2022-06-29 | H73: 2023-01-20 | Q73: ⬜ À enrichir
A74: 166 | B74: Rayane | C74: EL AOUEDJ | D74: 2023 | E74: RH | F74: Bénévole | G74: 2022-05-10 | H74: 2023-02-17 | Q74: ⬜ À enrichir
A75: 169 | B75: Lokmane | C75: EL OMARI | D75: 2023 | E75: IT | F75: Conventioné | G75: 2023-06-08 | H75: 2023-09-08 | Q75: ⬜ À enrichir
A76: 170 | B76: Amal | C76: ELHMAIDI | D76: 2023 | E76: RH | F76: Bénévole | G76: 2024-02-15 | H76: 2023-08-18 | Q76: ⬜ À enrichir
A77: 173 | B77: Davy | C77: ETCHEGARAY | D77: 2023 | E77: IT | F77: Conventioné | G77: 2023-01-19 | H77: 2023-04-21 | Q77: ⬜ À enrichir
A78: 176 | B78: Fatima | C78: EZ ZAHRA MALI | D78: 2023 | E78: CM | F78: Bénévole | G78: 2023-08-16 | H78: 2024-03-08 | Q78: ⬜ À enrichir
... A86: 191 | B86: Anis | C86: FTOUHI | D86: 2023 | E86: RH | F86: Bénévole | G86: 2023-02-01 | H86: 2023-08-04 | Q86: ⬜ À enrichir
A87: 193 | B87: Zully | C87: Faralli | D87: 2023 | E87: Osez l'entreponoriat - marketing opérationnale sociologie d'entreprise Statistique recherche - Trent | F87: Bénévole | G87: 2023-10-30 | H87: 2024-05-24 | I87: Non | Q87: ⬜ À enrichir
A88: 194 | B88: Sadia | C88: Franck Tao | D88: 2023 | E88: QVT SLP Référentiel : Empreinte chromatique | F88: Bénévole | G88: 2022-08-02 | H88: 14/0772026 | Q88: ⬜ À enrichir
A89: 198 | B89: RANIA | C89: GAIDA | D89: 2023 | E89: Juridique | F89: Bénévole | G89: 2023-05-15 | H89: 2023-11-17 | I89: Non | Q89: ⬜ À enrichir
A90: 199 | B90: Marko | C90: GAJIC | D90: 2023 | E90: GCC/ SC/ Partenariat | F90: Conventioné | G90: 2023-10-16 | H90: 2024-02-09 | Q90: ⬜ À enrichir
A91: 202 | B91: Marta | C91: GARZOZZO | D91: 2023 | E91: RH | F91: Bénévole | G91: 2022-01-26 | H91: 2022-07-29 | Q91: ⬜ À enrichir
A92: 205 | B92: Clémentine | C92: GIRARD | D92: 2023 | E92: RH | F92: Conventioné | G92: 2022-11-30 | H92: 2023-08-04 | Q92: ⬜ À enrichir
A93: 208 | B93: Julie | C93: GOUIN | D93: 2023 | E93: IT | F93: Bénévole | G93: 2023-10-12 | H93: 2023-04-05 | Q93: ⬜ À enrichir
A94: 210 | B94: Laura | C94: GRENIER | D94: 2023 | E94: RH | F94: Conventioné | G94: 2022-11-02 | H94: 2023-02-10 | Q94: ⬜ À enrichir
A95: 211 | B95: Isabelle | C95: GRISAR | D95: 2023 | E95: RH | F95: Bénévole | G95: 2022-06-06 | H95: 2023-01-27 | Q95: ⬜ À enrichir
A96: 215 | B96: Romain | C96: GUITTON | D96: 2023 | E96: RH | F96: Conventioné | G96: 2022-04-13 | H96: 2022-07-29 | Q96: ⬜ À enrichir
A97: 219 | B97: Romain | C97: Gras | D97: 2023 | E97: IT | F97: Bénévole | G97: 2023-07-20 | H97: 2023-10-20 | I97: Non | Q97: ⬜ À enrichir
A98: 221 | B98: Tidiane | C98: Gueye | D98: 2023 | E98: Branding - Repertoire Vert CM Partenariat | F98: Conventioné | G98: 2023-04-24 | H98: 2023-09-29 | I98: Non | Q98: ⬜ À enrichir
A99: 223 | B99: Florentin | C99: HARMAND | D99: 2023 | E99: IT | F99: Conventioné | G99: 2023-03-09 | H99: 2023-06-02 | Q99: ⬜ À enrichir
A100: 225 | B100: Hugo | C100: HENCK | D100: 2023 | E100: Publication | F100: Bénévole | G100: 2022-11-08 | H100: 2023-05-26 | Q100: ⬜ À enrichir
A101: 226 | B101: Kevin | C101: HERVE | D101: 2023 | E101: Agriculture durable | F101: Bénévole | G101: 2023-02-07 | H101: 2023-05-05 | Q101: ⬜ À enrichir
A102: 227 | B102: Nouhaila | C102: HIKMI | D102: 2023 | E102: IT | F102: Conventioné | G102: 2023-03-09 | H102: 2023-08-04 | Q102: ⬜ À enrichir
A103: 230 | B103: Anais | C103: HOFFMANN | D103: 2023 | E103: RH | F103: Conventioné | G103: 2023-05-04 | H103: 2023-07-05 | Q103: ⬜ À enrichir
A104: 231 | B104: Esquilin Balt | C104: HOUNDOFI | D104: 2023 | E104: Smart cities/ Agriculture durable | F104: Bénévole | G104: 2023-10-10 | H104: 2024-05-03 | Q104: ⬜ À enrichir
A105: 233 | B105: Lejla | C105: HUSELJIC | D105: 2023 | E105: Eco conso scientifique cosmétique durable | F105: Bénévole | G105: 2022-10-17 | H105: 2023-05-12 | Q105: ⬜ À enrichir
A106: 235 | B106: Wejden | C106: Harrabi | D106: 2023 | E106: SC GCC et formation | F106: Bénévole | G106: 2024-01-22 | H106: 2024-12-24 | I106: Non | Q106: ⬜ À enrichir
A107: 239 | B107: Nesrine | C107: Ishak Shaiek | D107: 2023 | E107: IT | F107: Conventioné | G107: 2023-11-06 | H107: 2023-03-12 | Q107: ⬜ À enrichir
A108: 242 | B108: Emilie | C108: JACQUIN | D108: 2023 | E108: Partenariat/ Branding | F108: Conventioné | G108: 2023-04-03 | H108: 2023-06-09 | Q108: ⬜ À enrichir
A109: 244 | B109: Ana | C109: JAURY | D109: 2023 | E109: RH | F109: Bénévole | G109: 2023-04-12 | H109: 2023-09-08 | I109: Alumni gratuit | Q109: ⬜ À enrichir
A110: 246 | B110: Guillaume | C110: JOURDE | D110: 2023 | E110: IT | F110: Conventioné | G110: 2022-10-13 | H110: 2023-01-27 | Q110: ⬜ À enrichir
A111: 248 | B111: Yassine | C111: Jedidi | D111: 2023 | E111: RV partenariat Branding et CM | F111: Conventioné | G111: 2023-01-16 | H111: 2023-05-17 | I111: Alumni gratuit | Q111: ⬜ À enrichir
A112: 250 | B112: Ettien | C112: KACOU | D112: 2023 | E112: Juridique | F112: Bénévole | G112: 2022-12-20 | H112: 2023-07-14 | Q112: ⬜ À enrichir
A113: 252 | B113: Mohamed | C113: KANN DIALLO | D113: 2023 | E113: RH | F113: Bénévole | G113: 2022-09-07 | H113: 2023-01-28 | Q113: ⬜ À enrichir
A114: 255 | B114: Alyssa | C114: KHADRAOUI | D114: 2023 | E114: Statistiques /SC | F114: Bénévole | G114: 2023-01-17 | H114: 2023-04-21 | Q114: ⬜ À enrichir
A115: 260 | B115: Camille | C115: KOUASSI | D115: 2023 | E115: Marketing | F115: Bénévole | G115: 2023-10-17 | H115: 2024-02-09 | Q115: ⬜ À enrichir
A116: 262 | B116: Ahmed | C116: KOWSAR | D116: 2023 | E116: RH | F116: Bénévole | G116: 2023-07-05 | H116: 2024-01-26 | Q116: ⬜ À enrichir
...

Sheet 📊 Stats
A1: 📊 Statistiques (auto-calculées)
A3: 🎯 VOLUMES CLÉS | D3: 🌍 PAR PAYS (post-enrichissement)
A4: Total alumni dans la base | B4: =COUNTA('Alumni AG'!B3:B512) | D4: Pays | E4: Nombre
A5: Enrichis via LinkedIn | B5: =COUNTIF('Alumni AG'!Q3:Q512,"✅ Enrichi") | D5: Suisse | E5: =COUNTIF('Alumni AG'!N3:N512,"Suisse")
A6: À enrichir | B6: =COUNTIF('Alumni AG'!Q3:Q512,"⬜ À enrichir") | D6: France | E6: =COUNTIF('Alumni AG'!N3:N512,"France")
A7: Introuvables LinkedIn | B7: =COUNTIF('Alumni AG'!Q3:Q512,"❌ Introuvable sur LinkedIn") | D7: Allemagne | E7: =COUNTIF('Alumni AG'!N3:N512,"Allemagne")
D8: Belgique | E8: =COUNTIF('Alumni AG'!N3:N512,"Belgique")
D9: Italie | E9: =COUNTIF('Alumni AG'!N3:N512,"Italie")
A10: 📅 PAR ANNÉE DE SORTIE | D10: Royaume-Uni | E10: =COUNTIF('Alumni AG'!N3:N512,"Royaume-Uni")
A11: Année | B11: Nombre | D11: Espagne | E11: =COUNTIF('Alumni AG'!N3:N512,"Espagne")
A12: 2023 | B12: =COUNTIF('Alumni AG'!D3:D512,2023) | D12: Portugal | E12: =COUNTIF('Alumni AG'!N3:N512,"Portugal")
A13: 2024 | B13: =COUNTIF('Alumni AG'!D3:D512,2024) | D13: États-Unis | E13: =COUNTIF('Alumni AG'!N3:N512,"États-Unis")
A14: 2025 | B14: =COUNTIF('Alumni AG'!D3:D512,2025) | D14: Canada | E14: =COUNTIF('Alumni AG'!N3:N512,"Canada")
A15: 2026 | B15: =COUNTIF('Alumni AG'!D3:D512,2026) | D15: Brésil | E15: =COUNTIF('Alumni AG'!N3:N512,"Brésil")
D16: Kenya | E16: =COUNTIF('Alumni AG'!N3:N512,"Kenya")
D17: Sénégal | E17: =COUNTIF('Alumni AG'!N3:N512,"Sénégal")
D18: Maroc | E18: =COUNTIF('Alumni AG'!N3:N512,"Maroc")
D19: Tunisie | E19: =COUNTIF('Alumni AG'!N3:N512,"Tunisie")
D20: Côte d'Ivoire | E20: =COUNTIF('Alumni AG'!N3:N512,"Côte d'Ivoire")
D21: Burkina Faso | E21: =COUNTIF('Alumni AG'!N3:N512,"Burkina Faso")
D22: Algérie | E22: =COUNTIF('Alumni AG'!N3:N512,"Algérie")
D23: Autre | E23: =COUNTIF('Alumni AG'!N3:N512,"Autre")
D26: 🎯 PAR SECTEUR
D27: Secteur | E27: Nombre
D28: Environnement / Climat | E28: =COUNTIF('Alumni AG'!O3:O512,"Environnement / Climat")
D29: Finance durable / ESG | E29: =COUNTIF('Alumni AG'!O3:O512,"Finance durable / ESG")
D30: Conseil / Audit | E30: =COUNTIF('Alumni AG'!O3:O512,"Conseil / Audit")
D31: Éducation / Recherche | E31: =COUNTIF('Alumni AG'!O3:O512,"Éducation / Recherche")
D32: ONG / Associatif | E32: =COUNTIF('Alumni AG'!O3:O512,"ONG / Associatif")
D33: Secteur public | E33: =COUNTIF('Alumni AG'!O3:O512,"Secteur public")
D34: Entreprise privée | E34: =COUNTIF('Alumni AG'!O3:O512,"Entreprise privée")
D35: Tech / Data | E35: =COUNTIF('Alumni AG'!O3:O512,"Tech / Data")
D36: Santé | E36: =COUNTIF('Alumni AG'!O3:O512,"Santé")
D37: Culture / Média | E37: =COUNTIF('Alumni AG'!O3:O512,"Culture / Média")
D38: Autre | E38: =COUNTIF('Alumni AG'!O3:O512,"Autre")

Sheet 🎯 Priorités
A1: 🎯 Alumni prioritaires pour enrichissement LinkedIn
A2: Stratégie: prioriser les alumni 2024-2025, qui sont partis récemment et sont le plus probablement visibles sur LinkedIn avec un poste actuel identifiable. Commence par le haut de cette liste.
A3: # | B3: Prénom | C3: Nom | D3: Année | E3: Fonction
A4: 1 | B4: Angela | C4: ABANKWA | D4: 2024 | E4: RH
A5: 2 | B5: Asmaà | C5: ABIDERRAHMANE | D5: 2024 | E5: IT
A6: 3 | B6: Andre | C6: ABLI | D6: 2024 | E6: Juridique
A7: 4 | B7: Johanna | C7: AEBI | D7: 2024 | E7: RH
A8: 5 | B8: Gérald | C8: AGBOTI | D8: 2024 | E8: Collaboteur agriculture durable
A9: 6 | B9: Yassh | C9: AGORO | D9: 2024 | E9: Data scientist
A10: 7 | B10: Yousra | C10: AL NASIR | D10: 2024 | E10: Coordinatrice recherche agriculture Durable
A11: 8 | B11: Jules-vianney | C11: ALIANA FOUDA | D11: 2024 | E11: Ingénieur éléctromagnétique
A12: 9 | B12: Alice | C12: ALVES PINTO | D12: 2024 | E12: Traductrice
A13: 10 | B13: Claire | C13: AMBLARD | D13: 2024 | E13: Design
A14: 11 | B14: Claire | C14: AMORY | D14: 2024 | E14: Coordinatrice GCBO
A15: 12 | B15: Anna-Maria | C15: ANNONAY | D15: 2024 | E15: Traductrice
... A153: 150 | B153: Alicx Maryse | C153: RABEMAHARAVO | D153: 2024 | E153: Coordinateur GCBO
